{
  "catalog_version": "2026-05-11.ws.22",
  "schema_version": "openfoundry.workshop.widget_catalog.v1",
  "items": [
    {
      "widget_type": "text",
      "widget_kind": "content",
      "label": "Text block",
      "description": "Markdown copy, briefing notes, and section headers.",
      "category": "content",
      "config_schema": {
        "type": "object",
        "additionalProperties": true,
        "properties": {
          "content": { "type": "string" },
          "align": { "type": "string", "enum": ["left", "center", "right"] }
        }
      },
      "input_variables": [],
      "output_variables": [],
      "events": [
        {
          "name": "click",
          "label": "Click",
          "description": "Runs configured click actions.",
          "action_kinds": ["set_variable", "navigate", "open_url", "refresh"],
          "payload_schema": { "type": "object", "properties": { "widget_id": { "type": "string" } } }
        }
      ],
      "permissions": ["app:read"],
      "display": {
        "icon": "document",
        "accent": "neutral",
        "tags": ["markdown", "copy"],
        "sort_order": 10,
        "preferred_chrome": "plain"
      },
      "default_props": { "content": "### New section\nAdd context for this workspace." },
      "default_size": { "width": 12, "height": 2 },
      "supported_bindings": [],
      "supports_children": false
    },
    {
      "widget_type": "metric",
      "widget_kind": "visualization",
      "label": "Metric",
      "description": "Metric card with grouped variable-backed values, numeric formatting, and conditional formatting.",
      "category": "analytics",
      "config_schema": {
        "type": "object",
        "additionalProperties": true,
        "properties": {
          "label": { "type": "string" },
          "metrics": {
            "type": "array",
            "items": {
              "type": "object",
              "additionalProperties": true,
              "properties": {
                "id": { "type": "string" },
                "label": { "type": "string" },
                "description": { "type": "string" },
                "value_type": { "type": "string", "enum": ["number", "string"] },
                "variable_id": { "type": "string" },
                "value": {},
                "format": {
                  "type": "object",
                  "additionalProperties": true,
                  "properties": {
                    "kind": { "type": "string", "enum": ["default", "number", "integer", "compact", "percent", "currency", "unit"] },
                    "precision": { "type": ["number", "string"] },
                    "unit": { "type": "string" },
                    "currency": { "type": "string" },
                    "prefix": { "type": "string" },
                    "suffix": { "type": "string" },
                    "empty_value": { "type": "string" }
                  }
                },
                "conditional_formatting": { "type": "array" },
                "secondary_metric": { "type": ["object", "null"] }
              }
            }
          },
          "layout_style": { "type": "string", "enum": ["card", "tag", "list"] },
          "direction": { "type": "string", "enum": ["horizontal", "vertical"] },
          "template": { "type": "string", "enum": ["stacked", "side_by_side"] },
          "metric_size": { "type": "string", "enum": ["compact", "regular", "large"] }
        }
      },
      "input_variables": [
        {
          "id": "value",
          "kind": "primitive",
          "label": "Metric variables",
          "description": "String, numeric, URL/runtime, aggregation, or function-backed variables displayed in the card.",
          "required": false
        }
      ],
      "output_variables": [],
      "events": [],
      "permissions": ["app:read", "data:read"],
      "display": {
        "icon": "sparkles",
        "accent": "green",
        "tags": ["kpi", "value"],
        "sort_order": 20,
        "preferred_chrome": "card"
      },
      "default_props": {
        "label": "Metric Card",
        "metrics": [
          {
            "id": "metric-1",
            "label": "Metric",
            "description": "",
            "value_type": "number",
            "variable_id": "",
            "value": "128",
            "format": { "kind": "number", "precision": 1 },
            "conditional_formatting": [],
            "secondary_metric": null
          }
        ],
        "layout_style": "card",
        "direction": "horizontal",
        "template": "stacked",
        "metric_size": "regular"
      },
      "default_size": { "width": 3, "height": 2 },
      "supported_bindings": ["query", "dataset", "object_set"],
      "supports_children": false
    },
    {
      "widget_type": "table",
      "widget_kind": "visualization",
      "label": "Table",
      "description": "Paginated records from query, dataset, or object set bindings.",
      "category": "analytics",
      "config_schema": {
        "type": "object",
        "additionalProperties": true,
        "properties": {
          "page_size": { "type": "integer", "minimum": 1 },
          "striped": { "type": "boolean" },
          "columns": { "type": "array", "items": { "type": "string" } }
        }
      },
      "input_variables": [
        {
          "id": "rows",
          "kind": "table",
          "label": "Rows",
          "description": "Rows from a query, dataset, ontology object set, or binding.",
          "required": false
        }
      ],
      "output_variables": [
        {
          "id": "selected_row",
          "kind": "row_selection",
          "label": "Selected row",
          "description": "The row selected by the user.",
          "required": false
        }
      ],
      "events": [
        {
          "name": "row_select",
          "label": "Row select",
          "description": "Runs when a row becomes selected.",
          "action_kinds": ["set_variable", "navigate", "refresh"],
          "payload_schema": { "type": "object", "properties": { "row_id": { "type": "string" } } }
        }
      ],
      "permissions": ["app:read", "data:read", "ontology:read"],
      "display": {
        "icon": "list",
        "accent": "blue",
        "tags": ["rows", "grid"],
        "sort_order": 30,
        "preferred_chrome": "card"
      },
      "default_props": { "page_size": 8, "striped": true },
      "default_size": { "width": 6, "height": 4 },
      "supported_bindings": ["query", "dataset", "ontology", "object_set"],
      "supports_children": false
    },
    {
      "widget_type": "object_table",
      "widget_kind": "object_set",
      "label": "Object table",
      "description": "Object-set table with selected object output.",
      "category": "core",
      "config_schema": {
        "type": "object",
        "additionalProperties": true,
        "properties": {
          "source_variable_id": { "type": "string" },
          "active_object_variable_id": { "type": "string" },
          "selected_object_set_variable_id": { "type": "string" },
          "columns": { "type": "array" },
          "default_sort_property": { "type": "string" },
          "default_sort_direction": { "type": "string", "enum": ["asc", "desc"] },
          "row_height_lines": { "type": "number", "minimum": 1 },
          "wrap_values": { "type": "boolean" },
          "multi_select": { "type": "boolean" },
          "disable_active_auto_selection": { "type": "boolean" },
          "enable_inline_edit": { "type": "boolean" },
          "row_actions": { "type": "array" }
        }
      },
      "input_variables": [
        {
          "id": "object_set",
          "kind": "object_set",
          "label": "Object set",
          "description": "Objects displayed as rows.",
          "required": true
        }
      ],
      "output_variables": [
        {
          "id": "active_object",
          "kind": "object_set_active_object",
          "label": "Active object",
          "description": "Highlighted row published as an active object variable.",
          "required": false
        },
        {
          "id": "selected_objects",
          "kind": "object_set_selection",
          "label": "Selected objects",
          "description": "Selected objects published as an object set variable.",
          "required": false
        }
      ],
      "events": [
        {
          "name": "select",
          "label": "Active object selection",
          "description": "Runs after the active row changes.",
          "action_kinds": ["set_variable", "navigate", "apply_action", "refresh"],
          "payload_schema": { "type": "object", "properties": { "object_id": { "type": "string" }, "object_type_id": { "type": "string" } } }
        },
        {
          "name": "selection_change",
          "label": "Selection change",
          "description": "Runs after row selection changes.",
          "action_kinds": ["set_variable", "navigate", "apply_action", "refresh"],
          "payload_schema": { "type": "object", "properties": { "object_ids": { "type": "array", "items": { "type": "string" } } } }
        },
        {
          "name": "row_action",
          "label": "Row action",
          "description": "Runs when a configured row action fires.",
          "action_kinds": ["set_variable", "navigate", "apply_action", "refresh"],
          "payload_schema": { "type": "object", "properties": { "row_action_id": { "type": "string" }, "object_id": { "type": "string" } } }
        }
      ],
      "permissions": ["app:read", "ontology:read"],
      "display": {
        "icon": "list",
        "accent": "blue",
        "tags": ["object-set", "selection"],
        "sort_order": 40,
        "preferred_chrome": "card"
      },
      "default_props": {
        "source_variable_id": "",
        "columns": [],
        "default_sort_property": "",
        "default_sort_direction": "asc",
        "row_height_lines": 1,
        "wrap_values": false,
        "multi_select": false,
        "active_object_variable_id": "",
        "selected_object_set_variable_id": "",
        "disable_active_auto_selection": false,
        "enable_inline_edit": false,
        "row_actions": []
      },
      "default_size": { "width": 7, "height": 4 },
      "supported_bindings": ["object_set"],
      "supports_children": false
    },
    {
      "widget_type": "filter_list",
      "widget_kind": "filter",
      "label": "Filter list",
      "description": "Filter controls backed by object set filter variables.",
      "category": "filtering",
      "config_schema": {
        "type": "object",
        "additionalProperties": true,
        "properties": {
          "source_variable_id": { "type": "string" },
          "output_variable_id": { "type": "string" },
          "filters": { "type": "array" },
          "layout": { "type": "string", "enum": ["vertical", "pills"] },
          "allow_add_remove": { "type": "boolean" }
        }
      },
      "input_variables": [
        {
          "id": "object_set",
          "kind": "object_set",
          "label": "Object set",
          "description": "Object set whose properties can be filtered.",
          "required": true
        }
      ],
      "output_variables": [
        {
          "id": "filters",
          "kind": "object_set_filter",
          "label": "Object-set filters",
          "description": "Object-set filter variable emitted by the widget.",
          "required": false
        }
      ],
      "events": [
        {
          "name": "filter_change",
          "label": "Filter change",
          "description": "Runs after filter values change.",
          "action_kinds": ["set_variable", "refresh"],
          "payload_schema": { "type": "object", "properties": { "filter_count": { "type": "integer" } } }
        }
      ],
      "permissions": ["app:read", "ontology:read"],
      "display": {
        "icon": "settings",
        "accent": "orange",
        "tags": ["filter", "object-set"],
        "sort_order": 50,
        "preferred_chrome": "panel"
      },
      "default_props": { "source_variable_id": "", "output_variable_id": "", "filters": [], "layout": "vertical", "allow_add_remove": false },
      "default_size": { "width": 4, "height": 4 },
      "supported_bindings": ["object_set"],
      "supports_children": false
    },
    {
      "widget_type": "property_list",
      "widget_kind": "object_set",
      "label": "Property list",
      "description": "Selected-object property display.",
      "category": "core",
      "config_schema": {
        "type": "object",
        "additionalProperties": true,
        "properties": {
          "source_variable_id": { "type": "string" },
          "items": { "type": "array" },
          "properties": { "type": "array" },
          "number_of_columns": { "type": "number", "minimum": 1, "maximum": 6 },
          "enable_value_wrapping": { "type": "boolean" },
          "hide_nulls": { "type": "boolean" },
          "value_layout": { "type": "string", "enum": ["adjacent", "below"] },
          "formats": { "type": "object" }
        }
      },
      "input_variables": [
        {
          "id": "input_object_set",
          "kind": "object_set",
          "label": "Input object set",
          "description": "Object set whose first object is displayed.",
          "required": true
        }
      ],
      "output_variables": [],
      "events": [],
      "permissions": ["app:read", "ontology:read"],
      "display": {
        "icon": "document",
        "accent": "teal",
        "tags": ["properties", "details"],
        "sort_order": 60,
        "preferred_chrome": "card"
      },
      "default_props": { "source_variable_id": "", "items": [], "properties": [], "number_of_columns": 2, "enable_value_wrapping": false, "hide_nulls": false, "value_layout": "adjacent", "formats": {} },
      "default_size": { "width": 4, "height": 4 },
      "supported_bindings": ["object_set"],
      "supports_children": false
    },
    {
      "widget_type": "object_set_title",
      "widget_kind": "object_set",
      "label": "Object set title",
      "description": "Object set count or single-object title with object type icon and empty-state behavior.",
      "category": "core",
      "config_schema": {
        "type": "object",
        "additionalProperties": true,
        "properties": {
          "source_variable_id": { "type": "string" },
          "contains_single_object": { "type": "boolean" },
          "show_icon": { "type": "boolean" },
          "title_override": { "type": "string" },
          "title_template": { "type": "string" },
          "render_when_empty": { "type": "boolean" },
          "empty_object_type_id": { "type": "string" },
          "empty_title": { "type": "string" }
        }
      },
      "input_variables": [
        {
          "id": "object_set",
          "kind": "object_set",
          "label": "Object set",
          "description": "Object set summarized by the title.",
          "required": true
        }
      ],
      "output_variables": [],
      "events": [],
      "permissions": ["app:read", "ontology:read"],
      "display": {
        "icon": "cube",
        "accent": "teal",
        "tags": ["title", "count", "object-set"],
        "sort_order": 70,
        "preferred_chrome": "plain"
      },
      "default_props": {
        "source_variable_id": "",
        "contains_single_object": false,
        "show_icon": true,
        "title_override": "",
        "render_when_empty": false,
        "empty_object_type_id": "",
        "empty_title": ""
      },
      "default_size": { "width": 4, "height": 2 },
      "supported_bindings": ["object_set"],
      "supports_children": false
    },
    {
      "widget_type": "chart",
      "widget_kind": "visualization",
      "label": "Chart",
      "description": "Line, bar, area, pie, or scatter visualizations.",
      "category": "analytics",
      "config_schema": {
        "type": "object",
        "additionalProperties": true,
        "properties": {
          "chart_type": { "type": "string", "enum": ["line", "bar", "area", "pie", "scatter"] },
          "x_field": { "type": "string" },
          "y_field": { "type": "string" },
          "series_field": { "type": "string" }
        }
      },
      "input_variables": [
        {
          "id": "data",
          "kind": "table",
          "label": "Chart data",
          "description": "Tabular data used to compute the chart series.",
          "required": false
        }
      ],
      "output_variables": [
        {
          "id": "selected_points",
          "kind": "chart_selection",
          "label": "Selected points",
          "description": "Selected chart marks or source rows.",
          "required": false
        }
      ],
      "events": [
        {
          "name": "mark_select",
          "label": "Mark select",
          "description": "Runs when a chart mark is selected.",
          "action_kinds": ["set_variable", "refresh"],
          "payload_schema": { "type": "object", "properties": { "series": { "type": "string" } } }
        }
      ],
      "permissions": ["app:read", "data:read"],
      "display": {
        "icon": "graph",
        "accent": "purple",
        "tags": ["visualization", "chart"],
        "sort_order": 80,
        "preferred_chrome": "card"
      },
      "default_props": { "chart_type": "line", "x_field": "label", "y_field": "value" },
      "default_size": { "width": 6, "height": 4 },
      "supported_bindings": ["query", "dataset", "object_set"],
      "supports_children": false
    },
    {
      "widget_type": "chart_xy",
      "widget_kind": "visualization",
      "label": "XY chart",
      "description": "Object-aware XY chart.",
      "category": "visualization",
      "config_schema": {
        "type": "object",
        "additionalProperties": true,
        "properties": {
          "layers": {
            "type": "array",
            "items": {
              "type": "object",
              "additionalProperties": true,
              "properties": {
                "id": { "type": "string" },
                "title": { "type": "string" },
                "data_input": { "type": "string", "enum": ["object_set", "function", "time_series"] },
                "source_variable_id": { "type": "string" },
                "object_type_id": { "type": "string" },
                "layer_type": { "type": "string", "enum": ["bar", "line", "scatter"] },
                "show_labels": { "type": "boolean" },
                "x_property": { "type": "string" },
                "x_bucketing": { "type": "string", "enum": ["exact", "range"] },
                "x_limit": { "type": "string" },
                "series_metric": { "type": "string", "enum": ["count", "sum", "avg", "min", "max", "approx_unique"] },
                "series_property": { "type": "string" },
                "cumulative_sum": { "type": "boolean" },
                "segment_by": { "type": "string" }
              }
            }
          },
          "show_legend": { "type": "boolean" },
          "show_tooltips": { "type": "boolean" },
          "bar_orientation": { "type": "string", "enum": ["horizontal", "vertical"] },
          "sort_by": { "type": "string", "enum": ["key_asc", "key_desc", "value_asc", "value_desc"] },
          "output_filter_variable_id": { "type": "string" },
          "selected_object_set_variable_id": { "type": "string" }
        }
      },
      "input_variables": [
        {
          "id": "object_set",
          "kind": "object_set",
          "label": "Object set",
          "description": "Object set plotted on the chart.",
          "required": true
        }
      ],
      "output_variables": [
        {
          "id": "selection_filter",
          "kind": "filter_output",
          "label": "Selection filter",
          "description": "Object set filter variable produced by selected chart categories.",
          "required": false
        },
        {
          "id": "selected_objects",
          "kind": "object_set_selection",
          "label": "Selected objects",
          "description": "Objects selected by chart interaction.",
          "required": false
        }
      ],
      "events": [
        {
          "name": "mark_select",
          "label": "Mark select",
          "description": "Runs when a chart mark is selected.",
          "action_kinds": ["set_variable", "refresh"],
          "payload_schema": {
            "type": "object",
            "properties": {
              "category": { "type": ["string", "null"] },
              "property_name": { "type": "string" },
              "object_ids": { "type": "array", "items": { "type": "string" } }
            }
          }
        }
      ],
      "permissions": ["app:read", "ontology:read"],
      "display": {
        "icon": "graph",
        "accent": "purple",
        "tags": ["object-set", "xy"],
        "sort_order": 90,
        "preferred_chrome": "card"
      },
      "default_props": {
        "layers": [
          {
            "id": "layer-1",
            "title": "Layer (bar)",
            "data_input": "object_set",
            "source_variable_id": "",
            "object_type_id": "",
            "layer_type": "bar",
            "show_labels": true,
            "x_property": "",
            "x_bucketing": "exact",
            "x_limit": "",
            "series_metric": "count",
            "series_property": "",
            "cumulative_sum": false,
            "segment_by": ""
          }
        ],
        "show_legend": false,
        "show_tooltips": true,
        "bar_orientation": "horizontal",
        "sort_by": "key_asc",
        "output_filter_variable_id": "",
        "selected_object_set_variable_id": ""
      },
      "default_size": { "width": 6, "height": 4 },
      "supported_bindings": ["object_set"],
      "supports_children": false
    },
    {
      "widget_type": "chart_pie",
      "widget_kind": "visualization",
      "label": "Pie chart",
      "description": "Object-aware pie chart.",
      "category": "visualization",
      "config_schema": {
        "type": "object",
        "additionalProperties": true,
        "properties": {
          "source_variable_id": { "type": "string" },
          "label_property": { "type": "string" },
          "value_property": { "type": "string" }
        }
      },
      "input_variables": [
        {
          "id": "object_set",
          "kind": "object_set",
          "label": "Object set",
          "description": "Object set aggregated into pie slices.",
          "required": true
        }
      ],
      "output_variables": [
        {
          "id": "selected_slice",
          "kind": "object_set_filter",
          "label": "Selected slice filter",
          "description": "Filter implied by a selected pie slice.",
          "required": false
        }
      ],
      "events": [
        {
          "name": "slice_select",
          "label": "Slice select",
          "description": "Runs when a pie slice is selected.",
          "action_kinds": ["set_variable", "refresh"],
          "payload_schema": { "type": "object", "properties": { "label": { "type": "string" } } }
        }
      ],
      "permissions": ["app:read", "ontology:read"],
      "display": {
        "icon": "graph",
        "accent": "purple",
        "tags": ["object-set", "pie"],
        "sort_order": 100,
        "preferred_chrome": "card"
      },
      "default_props": { "source_variable_id": "", "label_property": "", "value_property": "" },
      "default_size": { "width": 5, "height": 4 },
      "supported_bindings": ["object_set"],
      "supports_children": false
    },
    {
      "widget_type": "free_form_analysis",
      "widget_kind": "visualization",
      "label": "Free-form Analysis",
      "description": "Runtime analysis path for exploring a bounded input object set with filters, tables, metrics, charts, and notes.",
      "category": "visualization",
      "config_schema": {
        "type": "object",
        "additionalProperties": true,
        "properties": {
          "source_variable_id": { "type": "string" },
          "object_type_id": { "type": "string" },
          "output_variable_id": { "type": "string" },
          "empty_state_header": { "type": "string" },
          "empty_state_description": { "type": "string" },
          "enable_path_saving": { "type": "boolean" },
          "max_rows": { "type": "number", "minimum": 1, "maximum": 10000 },
          "cards": {
            "type": "array",
            "items": {
              "type": "object",
              "additionalProperties": true,
              "properties": {
                "id": { "type": "string" },
                "kind": { "type": "string", "enum": ["table", "metric", "filter", "bar_chart", "line_chart", "pie_chart", "text"] },
                "title": { "type": "string" },
                "property": { "type": "string" },
                "metric": { "type": "string", "enum": ["count", "sum", "avg", "min", "max", "approx_unique"] },
                "value": {},
                "columns": { "type": "array", "items": { "type": "string" } },
                "category_property": { "type": "string" },
                "value_property": { "type": "string" },
                "operator": { "type": "string", "enum": ["contains", "equals", "not_equals", "gte", "lte", "gt", "lt"] },
                "content": { "type": "string" }
              }
            }
          }
        }
      },
      "input_variables": [
        {
          "id": "input_object_set",
          "kind": "object_set",
          "label": "Input object set",
          "description": "The bounded object set users can explore in the runtime widget.",
          "required": true
        }
      ],
      "output_variables": [
        {
          "id": "output_object_set",
          "kind": "object_set_selection",
          "label": "Output object set",
          "description": "The filtered object set emitted by the current analysis path.",
          "required": false
        }
      ],
      "events": [
        {
          "name": "output_change",
          "label": "Output object set changed",
          "description": "Runs when filters or search change the output object set.",
          "action_kinds": ["set_variable", "refresh", "export"],
          "payload_schema": {
            "type": "object",
            "properties": {
              "object_type_id": { "type": "string" },
              "object_ids": { "type": "array", "items": { "type": "string" } },
              "row_count": { "type": "integer" }
            }
          }
        }
      ],
      "permissions": ["app:read", "ontology:read"],
      "display": {
        "icon": "graph",
        "accent": "purple",
        "tags": ["analysis", "object-set", "exploration"],
        "sort_order": 105,
        "preferred_chrome": "card"
      },
      "default_props": {
        "source_variable_id": "",
        "object_type_id": "",
        "output_variable_id": "",
        "empty_state_header": "Start a free-form analysis",
        "empty_state_description": "Add filters, metrics, tables, charts, and notes against this app-bounded object set.",
        "enable_path_saving": false,
        "max_rows": 5000,
        "cards": []
      },
      "default_size": { "width": 8, "height": 5 },
      "supported_bindings": ["object_set"],
      "supports_children": false
    },
    {
      "widget_type": "scenario",
      "widget_kind": "control",
      "label": "Scenario controls",
      "description": "What-if parameters that feed runtime bindings, scenario variables, charts, tables, and action forms.",
      "category": "workshop",
      "config_schema": {
        "type": "object",
        "additionalProperties": true,
        "properties": {
          "headline": { "type": "string" },
          "output_variable_id": { "type": "string" },
          "parameters": { "type": "array" },
          "apply_label": { "type": "string" },
          "reset_label": { "type": "string" },
          "summary_template": { "type": "string" }
        }
      },
      "input_variables": [],
      "output_variables": [
        {
          "id": "scenario_values",
          "kind": "scenario",
          "label": "Scenario values",
          "description": "Current what-if parameter values.",
          "required": false
        }
      ],
      "events": [
        {
          "name": "scenario_change",
          "label": "Apply scenario",
          "description": "Runs when scenario values are applied. Payload includes values, baseline, deltas, and changed parameter names.",
          "action_kinds": ["set_parameters", "set_variable", "refresh", "apply_action"],
          "payload_schema": {
            "type": "object",
            "properties": {
              "kind": { "type": "string", "const": "scenario" },
              "values": { "type": "object" },
              "baseline": { "type": "object" },
              "deltas": { "type": "object" }
            }
          }
        },
        {
          "name": "scenario_reset",
          "label": "Reset scenario",
          "description": "Runs when scenario values are reset to baseline.",
          "action_kinds": ["clear_parameters", "set_variable", "refresh"],
          "payload_schema": { "type": "object", "properties": { "kind": { "type": "string", "const": "scenario" } } }
        }
      ],
      "permissions": ["app:read"],
      "display": {
        "icon": "settings",
        "accent": "orange",
        "tags": ["scenario", "control"],
        "sort_order": 110,
        "preferred_chrome": "panel"
      },
      "default_props": {
        "headline": "Scenario controls",
        "output_variable_id": "",
        "parameters": [
          { "name": "demand_multiplier", "label": "Demand multiplier", "type": "number", "default_value": "1.0" }
        ],
        "apply_label": "Apply scenario",
        "reset_label": "Reset",
        "summary_template": "Demand multiplier: {{demand_multiplier}}"
      },
      "default_size": { "width": 5, "height": 4 },
      "supported_bindings": [],
      "supports_children": false
    },
    {
      "widget_type": "agent",
      "widget_kind": "ai",
      "label": "Embedded agent",
      "description": "Prompt box backed by an OpenFoundry agent.",
      "category": "ai",
      "config_schema": {
        "type": "object",
        "additionalProperties": true,
        "properties": {
          "agent_id": { "type": "string" },
          "welcome_message": { "type": "string" },
          "submit_label": { "type": "string" }
        },
        "required": ["agent_id"]
      },
      "input_variables": [
        {
          "id": "context",
          "kind": "primitive_or_object_set",
          "label": "Agent context",
          "description": "Optional variable context sent with the prompt.",
          "required": false
        }
      ],
      "output_variables": [
        {
          "id": "response",
          "kind": "agent_response",
          "label": "Agent response",
          "description": "Latest response returned by the embedded agent.",
          "required": false
        }
      ],
      "events": [
        {
          "name": "submit",
          "label": "Submit",
          "description": "Runs when a prompt is submitted.",
          "action_kinds": ["invoke_agent", "set_variable"],
          "payload_schema": { "type": "object", "properties": { "prompt": { "type": "string" } } }
        }
      ],
      "permissions": ["app:read", "agent:invoke"],
      "display": {
        "icon": "sparkles",
        "accent": "violet",
        "tags": ["agent", "ai"],
        "sort_order": 120,
        "preferred_chrome": "card"
      },
      "default_props": {
        "agent_id": "",
        "welcome_message": "Ask the embedded agent for help.",
        "submit_label": "Run agent"
      },
      "default_size": { "width": 7, "height": 4 },
      "supported_bindings": [],
      "supports_children": false
    },
    {
      "widget_type": "button",
      "widget_kind": "action",
      "label": "Action button",
      "description": "Trigger navigation, links, filters, or workflow actions.",
      "category": "actions",
      "config_schema": {
        "type": "object",
        "additionalProperties": true,
        "properties": {
          "label": { "type": "string" },
          "variant": { "type": "string", "enum": ["primary", "secondary", "danger"] },
          "events": { "type": "array" }
        }
      },
      "input_variables": [
        {
          "id": "action_context",
          "kind": "primitive_or_object_set",
          "label": "Action context",
          "description": "Optional context passed to button actions.",
          "required": false
        }
      ],
      "output_variables": [],
      "events": [
        {
          "name": "click",
          "label": "Click",
          "description": "Runs when the button is clicked.",
          "action_kinds": ["set_variable", "navigate", "open_url", "apply_action", "refresh", "export"],
          "payload_schema": { "type": "object" }
        }
      ],
      "permissions": ["app:read", "action:execute"],
      "display": {
        "icon": "run",
        "accent": "green",
        "tags": ["action", "button"],
        "sort_order": 130,
        "preferred_chrome": "plain"
      },
      "default_props": { "label": "Run action", "variant": "primary" },
      "default_size": { "width": 3, "height": 1 },
      "supported_bindings": [],
      "supports_children": false
    },
    {
      "widget_type": "button_group",
      "widget_kind": "action",
      "label": "Button group",
      "description": "Trigger one or more Workshop actions.",
      "category": "actions",
      "config_schema": {
        "type": "object",
        "additionalProperties": true,
        "properties": {
          "buttons": { "type": "array" },
          "orientation": { "type": "string", "enum": ["horizontal", "vertical"] }
        }
      },
      "input_variables": [
        {
          "id": "action_context",
          "kind": "primitive_or_object_set",
          "label": "Action context",
          "description": "Optional context passed to group actions.",
          "required": false
        }
      ],
      "output_variables": [
        {
          "id": "last_action",
          "kind": "primitive",
          "label": "Last action",
          "description": "Identifier of the most recent button action.",
          "required": false
        }
      ],
      "events": [
        {
          "name": "button_click",
          "label": "Button click",
          "description": "Runs when a button in the group is clicked.",
          "action_kinds": ["set_variable", "navigate", "open_url", "apply_action", "refresh", "export"],
          "payload_schema": { "type": "object", "properties": { "button_id": { "type": "string" } } }
        }
      ],
      "permissions": ["app:read", "action:execute"],
      "display": {
        "icon": "run",
        "accent": "green",
        "tags": ["action", "group"],
        "sort_order": 140,
        "preferred_chrome": "plain"
      },
      "default_props": { "buttons": [] },
      "default_size": { "width": 4, "height": 2 },
      "supported_bindings": [],
      "supports_children": false
    },
    {
      "widget_type": "map",
      "widget_kind": "geospatial",
      "label": "Map",
      "description": "MapLibre object, overlay, and template layers with points, lines, polygons, selection, shape drawing, and tooltips.",
      "category": "spatial",
      "config_schema": {
        "type": "object",
        "additionalProperties": true,
        "properties": {
          "base_layer_kind": { "type": "string", "enum": ["blank", "raster"] },
          "base_tile_url": { "type": "string" },
          "center_lat": { "type": "number" },
          "center_lon": { "type": "number" },
          "zoom": { "type": "number", "minimum": 0, "maximum": 22 },
          "show_legend": { "type": "boolean" },
          "map_template_id": { "type": "string" },
          "template_parameter_values": { "type": "object", "additionalProperties": true },
          "template_parameter_mappings": {
            "type": "array",
            "items": {
              "type": "object",
              "additionalProperties": true,
              "properties": {
                "parameter_id": { "type": "string" },
                "variable_id": { "type": "string" }
              }
            }
          },
          "layers": {
            "type": "array",
            "items": {
              "type": "object",
              "additionalProperties": true,
              "properties": {
                "id": { "type": "string" },
                "title": { "type": "string" },
                "source": { "type": "string", "enum": ["binding", "object_set", "object_type", "geospatial_tile"] },
                "source_variable_id": { "type": "string" },
                "visibility_variable_id": { "type": "string" },
                "object_type_id": { "type": "string" },
                "loading_mode": { "type": "string", "enum": ["eager", "viewport_tiles"] },
                "tile_layer_id": { "type": "string" },
                "geometry_type": { "type": "string", "enum": ["auto", "point", "line", "polygon"] },
                "latitude_field": { "type": "string" },
                "longitude_field": { "type": "string" },
                "geometry_field": { "type": "string" },
                "label_field": { "type": "string" },
                "color": { "type": "string" },
                "visible": { "type": "boolean" },
                "locked": { "type": "boolean" },
                "cluster_enabled": { "type": "boolean" }
              }
            }
          },
          "overlay_layers": {
            "type": "array",
            "items": {
              "type": "object",
              "additionalProperties": true,
              "properties": {
                "id": { "type": "string" },
                "title": { "type": "string" },
                "source": { "type": "string", "enum": ["geojson_url", "mvt_url", "saved_map_layer", "raster_url"] },
                "visibility_variable_id": { "type": "string" },
                "url": { "type": "string" },
                "resource_id": { "type": "string" },
                "source_layer": { "type": "string" },
                "geometry_type": { "type": "string", "enum": ["auto", "point", "line", "polygon"] },
                "color": { "type": "string" },
                "visible": { "type": "boolean" },
                "opacity": { "type": "number" }
              }
            }
          },
          "output_variable_id": { "type": "string" },
          "output_object_set_variable_id": { "type": "string" },
          "output_shape_variable_id": { "type": "string" },
          "shape_search_output_variable_id": { "type": "string" },
          "enable_shape_drawing": { "type": "boolean" },
          "time_configuration": {
            "type": "object",
            "additionalProperties": true,
            "properties": {
              "enabled": { "type": "boolean" },
              "open_by_default": { "type": "boolean" },
              "allow_change_selected_time": { "type": "boolean" },
              "show_live_mode_toggle": { "type": "boolean" },
              "time_zone": { "type": "string", "enum": ["local", "utc"] },
              "time_format": { "type": "string", "enum": ["12h", "24h", "local"] },
              "event_time_field": { "type": "string" },
              "selected_time_variable_id": { "type": "string" },
              "time_window_start_variable_id": { "type": "string" },
              "time_window_end_variable_id": { "type": "string" },
              "playback_state_variable_id": { "type": "string" },
              "playback_position_variable_id": { "type": "string" },
              "auto_pause_at_variable_id": { "type": "string" },
              "playback_speed_ms": { "type": "number", "minimum": 50, "maximum": 60000 },
              "window_step_ms": { "type": "number", "minimum": 1000 }
            }
          }
        }
      },
      "input_variables": [
        {
          "id": "layers",
          "kind": "table_or_object_set",
          "label": "Layer data",
          "description": "Object sets, queries, datasets, or saved geospatial layers rendered on the map.",
          "required": false
        }
      ],
      "output_variables": [
        {
          "id": "active_object",
          "kind": "object",
          "label": "Active object",
          "description": "Object currently clicked or focused on the map.",
          "required": false
        },
        {
          "id": "selected_objects",
          "kind": "object_set_selection",
          "label": "Selected objects",
          "description": "Map-selected objects as an object set variable.",
          "required": false
        },
        {
          "id": "drawn_shape",
          "kind": "geojson_shape",
          "label": "Drawn shape",
          "description": "GeoJSON shape drawn by the user.",
          "required": false
        },
        {
          "id": "shape_search_results",
          "kind": "object_set",
          "label": "Shape search results",
          "description": "Objects intersecting the drawn shape.",
          "required": false
        },
        {
          "id": "selected_time",
          "kind": "timestamp",
          "label": "Selected time",
          "description": "Bidirectional timestamp cursor on the timeline panel.",
          "required": false
        },
        {
          "id": "playback_position",
          "kind": "number",
          "label": "Playback position",
          "description": "Current playback time as milliseconds since epoch.",
          "required": false
        }
      ],
      "events": [
        {
          "name": "object_select",
          "label": "Object select",
          "description": "Runs when a map feature is selected.",
          "action_kinds": ["set_variable", "navigate", "apply_action", "refresh"],
          "payload_schema": { "type": "object", "properties": { "object_id": { "type": "string" } } }
        },
        {
          "name": "shape_change",
          "label": "Shape change",
          "description": "Runs when a drawn shape changes.",
          "action_kinds": ["set_variable", "refresh"],
          "payload_schema": { "type": "object", "properties": { "geojson": { "type": "object" } } }
        },
        {
          "name": "time_change",
          "label": "Time change",
          "description": "Runs when the timeline cursor or playback position changes.",
          "action_kinds": ["set_variable", "refresh"],
          "payload_schema": { "type": "object", "properties": { "selected_time_ms": { "type": "number" }, "window_start_ms": { "type": "number" }, "window_end_ms": { "type": "number" } } }
        }
      ],
      "permissions": ["app:read", "geospatial:read", "ontology:read"],
      "display": {
        "icon": "object",
        "accent": "blue",
        "tags": ["map", "geojson", "object-set"],
        "sort_order": 150,
        "preferred_chrome": "tool"
      },
      "default_props": {
        "base_layer_kind": "blank",
        "center_lat": 40.015,
        "center_lon": -105.2705,
        "zoom": 11,
        "show_legend": true,
        "latitude_field": "lat",
        "longitude_field": "lon",
        "label_field": "label",
        "layers": [
          {
            "id": "points",
            "title": "Objects",
            "source": "binding",
            "loading_mode": "eager",
            "source_variable_id": "",
            "visibility_variable_id": "",
            "geometry_type": "point",
            "latitude_field": "lat",
            "longitude_field": "lon",
            "label_field": "label",
            "color": "#2d72d2",
            "visible": true
          }
        ],
        "time_configuration": {
          "enabled": false,
          "open_by_default": false,
          "allow_change_selected_time": true,
          "show_live_mode_toggle": true,
          "time_zone": "local",
          "time_format": "local",
          "event_time_field": "",
          "selected_time_variable_id": "",
          "time_window_start_variable_id": "",
          "time_window_end_variable_id": "",
          "playback_state_variable_id": "",
          "playback_position_variable_id": "",
          "auto_pause_at_variable_id": "",
          "playback_speed_ms": 1000,
          "window_step_ms": 3600000
        }
      },
      "default_size": { "width": 8, "height": 4 },
      "supported_bindings": ["query", "dataset", "object_set"],
      "supports_children": false
    },
    {
      "widget_type": "timeline",
      "widget_kind": "visualization",
      "label": "Timeline",
      "description": "Visualize temporal data, rendering objects as chronologically ordered events. Supports multiple layers, vertical or horizontal orientation, and selection output.",
      "category": "visualization",
      "config_schema": {
        "type": "object",
        "additionalProperties": true,
        "properties": {
          "layers": {
            "type": "array",
            "items": {
              "type": "object",
              "additionalProperties": true,
              "properties": {
                "id": { "type": "string" },
                "title": { "type": "string" },
                "source_variable_id": { "type": "string" },
                "object_type_id": { "type": "string" },
                "scenario_variable_id": { "type": "string" },
                "date_property": { "type": "string" },
                "title_mode": { "type": "string", "enum": ["object_title", "property", "custom"] },
                "title_property": { "type": "string" },
                "custom_title": { "type": "string" },
                "properties_mode": { "type": "string", "enum": ["prominent", "specific"] },
                "displayed_properties": { "type": "array", "items": { "type": "string" } },
                "color_mode": { "type": "string", "enum": ["default", "static", "dynamic"] },
                "color": { "type": "string" },
                "color_rules": {
                  "type": "array",
                  "items": {
                    "type": "object",
                    "additionalProperties": true,
                    "properties": {
                      "property_name": { "type": "string" },
                      "operator": { "type": "string", "enum": ["equals", "in", "gte", "lte", "gt", "lt"] },
                      "value": {},
                      "color": { "type": "string" }
                    }
                  }
                },
                "icon_mode": { "type": "string", "enum": ["default", "none", "custom"] },
                "icon": { "type": "string" },
                "selection_event_override": { "type": "string" }
              }
            }
          },
          "orientation": { "type": "string", "enum": ["vertical", "horizontal"] },
          "order": { "type": "string", "enum": ["newest_first", "oldest_first"] },
          "show_legend": { "type": "boolean" },
          "show_time_between_events": { "type": "boolean" },
          "highlight_selection": { "type": "boolean" },
          "selected_object_variable_id": { "type": "string" },
          "selected_objects_variable_id": { "type": "string" },
          "selected_layer_variable_id": { "type": "string" },
          "empty_label": { "type": "string" },
          "max_events": { "type": "number", "minimum": 1, "maximum": 5000 }
        }
      },
      "input_variables": [
        {
          "id": "object_set",
          "kind": "object_set",
          "label": "Object set",
          "description": "Primary object set whose objects are rendered as timeline events.",
          "required": true
        }
      ],
      "output_variables": [
        {
          "id": "active_object",
          "kind": "object",
          "label": "Active object",
          "description": "Currently selected timeline event as an object set of one.",
          "required": false
        },
        {
          "id": "selection_filter",
          "kind": "filter_output",
          "label": "Selection filter",
          "description": "Object set filter variable produced by event selection.",
          "required": false
        }
      ],
      "events": [
        {
          "name": "event_select",
          "label": "Event select",
          "description": "Runs when an event on the timeline is selected.",
          "action_kinds": ["set_variable", "navigate", "apply_action", "refresh"],
          "payload_schema": {
            "type": "object",
            "properties": {
              "object_id": { "type": "string" },
              "layer_id": { "type": "string" },
              "event_time_ms": { "type": "number" }
            }
          }
        }
      ],
      "permissions": ["app:read", "ontology:read"],
      "display": {
        "icon": "history",
        "accent": "blue",
        "tags": ["object-set", "temporal"],
        "sort_order": 95,
        "preferred_chrome": "card"
      },
      "default_props": {
        "layers": [
          {
            "id": "layer-1",
            "title": "Events",
            "source_variable_id": "",
            "object_type_id": "",
            "date_property": "",
            "title_mode": "object_title",
            "title_property": "",
            "custom_title": "",
            "properties_mode": "specific",
            "displayed_properties": [],
            "color_mode": "default",
            "color": "#2d72d2",
            "color_rules": [],
            "icon_mode": "default",
            "icon": "calendar",
            "selection_event_override": ""
          }
        ],
        "orientation": "vertical",
        "order": "newest_first",
        "show_legend": false,
        "show_time_between_events": true,
        "highlight_selection": true,
        "selected_object_variable_id": "",
        "selected_objects_variable_id": "",
        "selected_layer_variable_id": "",
        "empty_label": "No timeline events to display.",
        "max_events": 250
      },
      "default_size": { "width": 6, "height": 5 },
      "supported_bindings": ["object_set"],
      "supports_children": false
    },
    {
      "widget_type": "vertex_graph_embed",
      "widget_kind": "embed",
      "label": "Vertex Graph",
      "description": "Embed a saved Vertex graph, graph template, or diagram inside the Workshop module. Selection sync is user→Workshop via `selected_objects`; Workshop can refocus the graph via `zoom_to`.",
      "category": "embed",
      "config_schema": {
        "type": "object",
        "additionalProperties": true,
        "properties": {
          "resource": {
            "type": "object",
            "additionalProperties": true,
            "properties": {
              "kind": { "type": "string", "enum": ["static", "variable", "override_rid"] },
              "rid": { "type": "string" },
              "variable_id": { "type": "string" },
              "override_rid": { "type": "string" }
            }
          },
          "sub_graph_variable_id": { "type": "string" },
          "refresh_key_variable_id": { "type": "string" },
          "append_on_parameter_change": { "type": "boolean" },
          "parameters": {
            "type": "array",
            "items": {
              "type": "object",
              "additionalProperties": true,
              "properties": {
                "id": { "type": "string" },
                "kind": { "type": "string", "enum": ["object_set", "string", "number", "boolean", "date", "timestamp"] },
                "variable_id": { "type": "string" },
                "static_value": {}
              }
            }
          },
          "scenario": {
            "type": "object",
            "additionalProperties": true,
            "properties": {
              "load_from_scenario": { "type": "boolean" },
              "regenerate_after_apply": { "type": "boolean" }
            }
          },
          "selected_objects_variable_id": { "type": "string" },
          "objects_on_subgraph_variable_id": { "type": "string" },
          "zoom_to_variable_id": { "type": "string" },
          "add_to_subgraph_variable_id": { "type": "string" },
          "available_actions": { "type": "string", "enum": ["all", "some", "none"] },
          "available_action_type_ids": { "type": "array", "items": { "type": "string" } },
          "capabilities": {
            "type": "object",
            "additionalProperties": true,
            "properties": {
              "read_only": { "type": "boolean" },
              "enable_transition_to_vertex": { "type": "boolean" },
              "enable_export_png": { "type": "boolean" }
            }
          },
          "panels": {
            "type": "object",
            "additionalProperties": true,
            "properties": {
              "legend": { "type": "boolean" },
              "series": { "type": "boolean" },
              "time_selection": { "type": "boolean" },
              "timeline": { "type": "boolean" },
              "layers": { "type": "boolean" },
              "selection": { "type": "boolean" },
              "search": { "type": "boolean" },
              "histogram": { "type": "boolean" },
              "info": { "type": "boolean" },
              "version_history": { "type": "boolean" },
              "add_object": { "type": "boolean" },
              "subgraph_navigation": { "type": "boolean" }
            }
          },
          "incomplete_inputs_message": { "type": "string" }
        }
      },
      "input_variables": [
        {
          "id": "zoom_to",
          "kind": "object_set",
          "label": "Zoom to object set",
          "description": "Object set the embedded graph should focus the viewport on. Workshop→graph is one-directional: the graph cannot reverse-select Workshop variables.",
          "required": false
        },
        {
          "id": "add_to_subgraph",
          "kind": "object_set",
          "label": "Add objects to subgraph",
          "description": "Programmatically append objects to the embedded graph's current subgraph.",
          "required": false
        }
      ],
      "output_variables": [
        {
          "id": "selected_objects",
          "kind": "object_set_selection",
          "label": "Selected objects",
          "description": "Auto-populated when the user selects one or more nodes in the embedded graph.",
          "required": false
        },
        {
          "id": "objects_on_subgraph",
          "kind": "object_set",
          "label": "Objects on subgraph",
          "description": "All objects currently rendered on the active subgraph.",
          "required": false
        }
      ],
      "events": [
        {
          "name": "selected_objects_change",
          "label": "Selected objects change",
          "description": "Runs when the embedded graph selection changes.",
          "action_kinds": ["set_variable", "navigate", "apply_action", "refresh"],
          "payload_schema": {
            "type": "object",
            "properties": {
              "object_ids": { "type": "array", "items": { "type": "string" } }
            }
          }
        },
        {
          "name": "successful_action_application",
          "label": "Successful action application",
          "description": "Runs after an action invoked from inside the embedded graph succeeds.",
          "action_kinds": ["set_variable", "navigate", "apply_action", "refresh"],
          "payload_schema": {
            "type": "object",
            "properties": {
              "action_type_id": { "type": "string" }
            }
          }
        }
      ],
      "permissions": ["app:read", "ontology:read", "vertex:read"],
      "display": {
        "icon": "graph",
        "accent": "purple",
        "tags": ["vertex", "graph", "link-analysis", "embed"],
        "sort_order": 170,
        "preferred_chrome": "card"
      },
      "default_props": {
        "resource": { "kind": "static", "rid": "", "variable_id": "", "override_rid": "" },
        "sub_graph_variable_id": "",
        "refresh_key_variable_id": "",
        "append_on_parameter_change": false,
        "parameters": [],
        "scenario": { "load_from_scenario": false, "regenerate_after_apply": false },
        "selected_objects_variable_id": "",
        "objects_on_subgraph_variable_id": "",
        "zoom_to_variable_id": "",
        "add_to_subgraph_variable_id": "",
        "available_actions": "all",
        "available_action_type_ids": [],
        "capabilities": {
          "read_only": true,
          "enable_transition_to_vertex": true,
          "enable_export_png": false
        },
        "panels": {
          "legend": true,
          "series": false,
          "time_selection": false,
          "timeline": false,
          "layers": false,
          "selection": true,
          "search": false,
          "histogram": false,
          "info": true,
          "version_history": false,
          "add_object": false,
          "subgraph_navigation": false
        },
        "incomplete_inputs_message": "Pick a saved Vertex graph in the inspector to render."
      },
      "default_size": { "width": 8, "height": 6 },
      "supported_bindings": ["object_set"],
      "supports_children": false
    },
    {
      "widget_type": "embedded_module",
      "widget_kind": "embed",
      "label": "Embedded module",
      "description": "Embed another published Workshop module and bind its module-interface variables to parent variables. Mapped variables share state in both directions; the parent's variable definition is authoritative and the child's default is ignored.",
      "category": "embed",
      "config_schema": {
        "type": "object",
        "additionalProperties": true,
        "properties": {
          "module_slug": {
            "type": "string",
            "description": "Slug of the published child module to embed."
          },
          "module_rid": {
            "type": "string",
            "description": "Optional resource id alias for the child module; takes precedence over module_slug when both are provided."
          },
          "mapping": {
            "type": "object",
            "additionalProperties": {
              "type": "object",
              "additionalProperties": true,
              "properties": {
                "kind": { "type": "string", "enum": ["variable", "literal", "runtime_parameter"] },
                "variable_id": { "type": "string" },
                "value": {}
              }
            },
            "description": "Maps child interface external ids to parent value sources. Keys are child external_ids."
          },
          "lazy_load": {
            "type": "boolean",
            "description": "Defer mounting the child until the embed scrolls into the viewport. Defaults to true."
          },
          "open_referenced_module_in_new_tab": {
            "type": "boolean"
          }
        }
      },
      "interface_mapping": "dynamic_from_target_module",
      "input_variables": [],
      "output_variables": [],
      "events": [],
      "permissions": ["app:read"],
      "display": {
        "icon": "applications",
        "accent": "blue",
        "tags": ["embed", "composition"],
        "sort_order": 175,
        "preferred_chrome": "card"
      },
      "default_props": {
        "module_slug": "",
        "module_rid": "",
        "mapping": {},
        "lazy_load": true,
        "open_referenced_module_in_new_tab": false
      },
      "default_size": { "width": 12, "height": 6 },
      "supported_bindings": [],
      "supports_children": false
    },
    {
      "widget_type": "container",
      "widget_kind": "layout",
      "label": "Container",
      "description": "Grouped nested widget section for composite layouts.",
      "category": "layout",
      "config_schema": {
        "type": "object",
        "additionalProperties": true,
        "properties": {
          "title": { "type": "string" },
          "variant": { "type": "string", "enum": ["plain", "card", "section"] }
        }
      },
      "input_variables": [],
      "output_variables": [],
      "events": [],
      "permissions": ["app:read"],
      "display": {
        "icon": "cube",
        "accent": "neutral",
        "tags": ["layout", "children"],
        "sort_order": 160,
        "preferred_chrome": "section"
      },
      "default_props": { "title": "Section", "variant": "card" },
      "default_size": { "width": 12, "height": 4 },
      "supported_bindings": [],
      "supports_children": true
    }
  ]
}
